<?xml version="1.0" encoding="utf-8" standalone="yes"?>
<Gesture Name="crossLeft" NumPts="64">
    <Point X="0" Y="0" Z="0" SIDE="0"/>
    <Point X="0,01921261" Y="-0,01538222" Z="0,002683916" SIDE="0"/>
    <Point X="0,03534438" Y="-0,03307165" Z="0,009027036" SIDE="0"/>
    <Point X="0,04949139" Y="-0,05174128" Z="0,01727527" SIDE="0"/>
    <Point X="0,0640446" Y="-0,06946729" Z="0,02677217" SIDE="0"/>
    <Point X="0,07748757" Y="-0,08700728" Z="0,03803056" SIDE="0"/>
    <Point X="0,08937356" Y="-0,1050511" Z="0,05027685" SIDE="0"/>
    <Point X="0,1004962" Y="-0,1243367" Z="0,06128873" SIDE="0"/>
    <Point X="0,1103161" Y="-0,1442557" Z="0,0723841" SIDE="0"/>
    <Point X="0,119367" Y="-0,1644498" Z="0,08364667" SIDE="0"/>
    <Point X="0,1276984" Y="-0,1848148" Z="0,09516881" SIDE="0"/>
    <Point X="0,1360219" Y="-0,2049164" Z="0,1071483" SIDE="0"/>
    <Point X="0,1442574" Y="-0,2249651" Z="0,1192768" SIDE="0"/>
    <Point X="0,1522944" Y="-0,2449869" Z="0,1315829" SIDE="0"/>
    <Point X="0,1598381" Y="-0,2652082" Z="0,1438678" SIDE="0"/>
    <Point X="0,1670742" Y="-0,2855541" Z="0,1561394" SIDE="0"/>
    <Point X="0,172721" Y="-0,3061649" Z="0,1687687" SIDE="0"/>
    <Point X="0,1779506" Y="-0,3268453" Z="0,1814918" SIDE="0"/>
    <Point X="0,1810081" Y="-0,3478352" Z="0,1943779" SIDE="0"/>
    <Point X="0,1836496" Y="-0,3688845" Z="0,2072953" SIDE="0"/>
    <Point X="0,185163" Y="-0,3899143" Z="0,2204092" SIDE="0"/>
    <Point X="0,1863442" Y="-0,4109385" Z="0,233581" SIDE="0"/>
    <Point X="0,1882195" Y="-0,4316581" Z="0,2471325" SIDE="0"/>
    <Point X="0,1905225" Y="-0,4521901" Z="0,260918" SIDE="0"/>
    <Point X="0,1930962" Y="-0,4724907" Z="0,2749825" SIDE="0"/>
    <Point X="0,1961419" Y="-0,4923878" Z="0,2895336" SIDE="0"/>
    <Point X="0,1991877" Y="-0,5122849" Z="0,3040846" SIDE="0"/>
    <Point X="0,2017393" Y="-0,5320601" Z="0,3188943" SIDE="0"/>
    <Point X="0,2042711" Y="-0,5518302" Z="0,3337144" SIDE="0"/>
    <Point X="0,2055537" Y="-0,571555" Z="0,3486946" SIDE="0"/>
    <Point X="0,2054283" Y="-0,5912285" Z="0,3638552" SIDE="0"/>
    <Point X="0,205303" Y="-0,610902" Z="0,3790157" SIDE="0"/>
    <Point X="0,2033917" Y="-0,6305251" Z="0,3940609" SIDE="0"/>
    <Point X="0,2004606" Y="-0,6501193" Z="0,4090403" SIDE="0"/>
    <Point X="0,1975295" Y="-0,6697134" Z="0,4240197" SIDE="0"/>
    <Point X="0,1897214" Y="-0,6882707" Z="0,438496" SIDE="0"/>
    <Point X="0,1815244" Y="-0,7067454" Z="0,4529322" SIDE="0"/>
    <Point X="0,1732545" Y="-0,7252026" Z="0,4673454" SIDE="0"/>
    <Point X="0,1637532" Y="-0,7433664" Z="0,4813706" SIDE="0"/>
    <Point X="0,1542518" Y="-0,7615303" Z="0,4953957" SIDE="0"/>
    <Point X="0,1434725" Y="-0,7791924" Z="0,509005" SIDE="0"/>
    <Point X="0,1304885" Y="-0,795989" Z="0,5218967" SIDE="0"/>
    <Point X="0,1175045" Y="-0,8127855" Z="0,5347885" SIDE="0"/>
    <Point X="0,1036811" Y="-0,8290157" Z="0,5474991" SIDE="0"/>
    <Point X="0,08919048" Y="-0,8447958" Z="0,5600657" SIDE="0"/>
    <Point X="0,07469988" Y="-0,8605757" Z="0,5726322" SIDE="0"/>
    <Point X="0,0599005" Y="-0,8756223" Z="0,5857155" SIDE="0"/>
    <Point X="0,0449935" Y="-0,8904131" Z="0,598979" SIDE="0"/>
    <Point X="0,02979088" Y="-0,9048795" Z="0,6121718" SIDE="0"/>
    <Point X="0,01091173" Y="-0,9153109" Z="0,6244872" SIDE="0"/>
    <Point X="-0,007967432" Y="-0,9257421" Z="0,6368028" SIDE="0"/>
    <Point X="-0,02731751" Y="-0,9363446" Z="0,6481723" SIDE="0"/>
    <Point X="-0,04699755" Y="-0,947067" Z="0,6588789" SIDE="0"/>
    <Point X="-0,06770495" Y="-0,9569055" Z="0,6681302" SIDE="0"/>
    <Point X="-0,08989988" Y="-0,9654645" Z="0,6752741" SIDE="0"/>
    <Point X="-0,1130216" Y="-0,9717454" Z="0,6788065" SIDE="0"/>
    <Point X="-0,1376173" Y="-0,9744033" Z="0,6765947" SIDE="0"/>
    <Point X="-0,162097" Y="-0,9779328" Z="0,6750701" SIDE="0"/>
    <Point X="-0,1863093" Y="-0,9834703" Z="0,6751286" SIDE="0"/>
    <Point X="-0,210457" Y="-0,9892407" Z="0,6755482" SIDE="0"/>
    <Point X="-0,2344942" Y="-0,9954087" Z="0,6765847" SIDE="0"/>
    <Point X="-0,258962" Y="-0,9988179" Z="0,6766611" SIDE="0"/>
    <Point X="-0,2837489" Y="-1" Z="0,6762002" SIDE="0"/>
    <Point X="-0,308418" Y="-0,9989104" Z="0,6788741" SIDE="0"/>
</Gesture>

