<?xml version="1.0" encoding="utf-8" standalone="yes"?>
<Gesture Name="thunderLeft" NumPts="64">
  <Point X="0" Y="0" Z="0" SIDE="0"/>
  <Point X="0" Y="-0.01269578" Z="0.04033654" SIDE="0"/>
  <Point X="0" Y="-0.001595266" Z="0.08730474" SIDE="0"/>
  <Point X="0" Y="0.02031555" Z="0.1303419" SIDE="0"/>
  <Point X="0" Y="0.04925562" Z="0.1690575" SIDE="0"/>
  <Point X="0" Y="0.08588758" Z="0.201073" SIDE="0"/>
  <Point X="0" Y="0.1235793" Z="0.2318123" SIDE="0"/>
  <Point X="0" Y="0.1646374" Z="0.2578669" SIDE="0"/>
  <Point X="0" Y="0.2071197" Z="0.281476" SIDE="0"/>
  <Point X="0" Y="0.2525305" Z="0.2981079" SIDE="0"/>
  <Point X="0" Y="0.2997596" Z="0.3096191" SIDE="0"/>
  <Point X="0" Y="0.3478313" Z="0.3164172" SIDE="0"/>
  <Point X="0" Y="0.3964226" Z="0.3141762" SIDE="0"/>
  <Point X="0" Y="0.4449315" Z="0.3104818" SIDE="0"/>
  <Point X="0" Y="0.4926891" Z="0.3011622" SIDE="0"/>
  <Point X="0" Y="0.5396343" Z="0.288515" SIDE="0"/>
  <Point X="0" Y="0.5857654" Z="0.2732611" SIDE="0"/>
  <Point X="0" Y="0.6278838" Z="0.2494631" SIDE="0"/>
  <Point X="0" Y="0.6648545" Z="0.2178998" SIDE="0"/>
  <Point X="0" Y="0.7019628" Z="0.186923" SIDE="0"/>
  <Point X="0" Y="0.7364329" Z="0.1528858" SIDE="0"/>
  <Point X="0" Y="0.767542" Z="0.1158942" SIDE="0"/>
  <Point X="0" Y="0.7932261" Z="0.07543161" SIDE="0"/>
  <Point X="0" Y="0.8145311" Z="0.03361493" SIDE="0"/>
  <Point X="0" Y="0.8347484" Z="-0.004895798" SIDE="0"/>
  <Point X="0" Y="0.8555652" Z="0.01190209" SIDE="0"/>
  <Point X="0" Y="0.8854018" Z="0.04422928" SIDE="0"/>
  <Point X="0" Y="0.9075175" Z="0.08405749" SIDE="0"/>
  <Point X="0" Y="0.921043" Z="0.1257282" SIDE="0"/>
  <Point X="0" Y="0.9275671" Z="0.1704245" SIDE="0"/>
  <Point X="0" Y="0.9280441" Z="0.2162692" SIDE="0"/>
  <Point X="0" Y="0.9205719" Z="0.2624211" SIDE="0"/>
  <Point X="0" Y="0.9042159" Z="0.3076965" SIDE="0"/>
  <Point X="0" Y="0.8816788" Z="0.3507537" SIDE="0"/>
  <Point X="0" Y="0.8541175" Z="0.3907123" SIDE="0"/>
  <Point X="0" Y="0.8241211" Z="0.4288036" SIDE="0"/>
  <Point X="0" Y="0.7903612" Z="0.463269" SIDE="0"/>
  <Point X="0" Y="0.7513016" Z="0.4911848" SIDE="0"/>
  <Point X="0" Y="0.7103133" Z="0.5163746" SIDE="0"/>
  <Point X="0" Y="0.6668022" Z="0.5354682" SIDE="0"/>
  <Point X="0" Y="0.6218734" Z="0.5518157" SIDE="0"/>
  <Point X="0" Y="0.5756529" Z="0.5649646" SIDE="0"/>
  <Point X="0" Y="0.5283511" Z="0.5688115" SIDE="0"/>
  <Point X="0" Y="0.4807781" Z="0.573292" SIDE="0"/>
  <Point X="0" Y="0.4330384" Z="0.5736119" SIDE="0"/>
  <Point X="0" Y="0.3854339" Z="0.5683104" SIDE="0"/>
  <Point X="0" Y="0.3386886" Z="0.5587016" SIDE="0"/>
  <Point X="0" Y="0.2924354" Z="0.5464517" SIDE="0"/>
  <Point X="0" Y="0.2470975" Z="0.5313297" SIDE="0"/>
  <Point X="0" Y="0.204411" Z="0.5101894" SIDE="0"/>
  <Point X="0" Y="0.1630147" Z="0.4863013" SIDE="0"/>
  <Point X="0" Y="0.1218452" Z="0.4617202" SIDE="0"/>
  <Point X="0" Y="0.08500884" Z="0.430903" SIDE="0"/>
  <Point X="0" Y="0.05021134" Z="0.3982844" SIDE="0"/>
  <Point X="0" Y="0.02207114" Z="0.3599238" SIDE="0"/>
  <Point X="0" Y="-0.001255231" Z="0.3182411" SIDE="0"/>
  <Point X="0" Y="-0.02000326" Z="0.2739141" SIDE="0"/>
  <Point X="0" Y="-0.03543766" Z="0.2280023" SIDE="0"/>
  <Point X="0" Y="-0.04687233" Z="0.1807436" SIDE="0"/>
  <Point X="0" Y="-0.05620513" Z="0.1331155" SIDE="0"/>
  <Point X="0" Y="-0.06478826" Z="0.08563918" SIDE="0"/>
  <Point X="0" Y="-0.0679694" Z="0.03770691" SIDE="0"/>
  <Point X="0" Y="-0.06906793" Z="-0.008979586" SIDE="0"/>
  <Point X="0" Y="-0.0719559" Z="-0.0003428486" SIDE="0"/>
</Gesture>